{
  "value_plays": [
    {
      "League": "NCAAB",
      "Event": "Kennesaw St @ Sam Houston",
      "Injury Alert": "\u2014",
      "Selection": "Sam Houston",
      "Market": "spreads",
      "Odds": -108,
      "Value (%)": 14.68,
      "Recommended Stake": 30.0,
      "Start Time": "Mar 13, 03:00 PM ET",
      "commence_time": "2026-03-13T19:00:00+00:00",
      "start_time": "2026-03-13T19:00:00+00:00",
      "model_prob": 0.5954283295257987,
      "implied_prob": 0.5,
      "point": -4.0,
      "home_team": "Sam Houston",
      "away_team": "Kennesaw St",
      "is_home_b2b": false,
      "is_away_b2b": false,
      "underdog_value": false,
      "line_error": -4.67,
      "confidence_tier": "High",
      "reasoning_summary": "Our model sees 14.7% expected value on Sam Houston -4.0 in this Spread\u2014the best NCAAB play we're highlighting today. Sam Houston BARTHAG 0.00 (win probability). Kennesaw St BARTHAG 0.00 (win probability)",
      "is_conference_tournament": false,
      "home_seed": null,
      "away_seed": null,
      "home_days_since_tournament_game": null,
      "away_days_since_tournament_game": null,
      "home_clinched_ncaa_bid": false,
      "away_clinched_ncaa_bid": false,
      "home_is_bubble_team": false,
      "away_is_bubble_team": false,
      "Point": -4.0
    },
    {
      "League": "NCAAB",
      "Event": "Wisconsin @ Illinois",
      "Injury Alert": "\u2014",
      "Selection": "Illinois",
      "Market": "spreads",
      "Odds": -114,
      "Value (%)": 12.32,
      "Recommended Stake": 30.0,
      "Start Time": "Mar 13, 02:30 PM ET",
      "commence_time": "2026-03-13T18:30:00+00:00",
      "start_time": "2026-03-13T18:30:00+00:00",
      "model_prob": 0.5983478998162399,
      "implied_prob": 0.5042122999157539,
      "point": -8.0,
      "home_team": "Illinois",
      "away_team": "Wisconsin",
      "is_home_b2b": false,
      "is_away_b2b": false,
      "underdog_value": false,
      "line_error": -12.54,
      "confidence_tier": "High",
      "reasoning_summary": "Our model sees 12.3% expected value on Illinois -8.0 in this Spread\u2014the best NCAAB play we're highlighting today. Illinois BARTHAG 0.00 (win probability). Wisconsin BARTHAG 0.00 (win probability)",
      "is_conference_tournament": false,
      "home_seed": null,
      "away_seed": null,
      "home_days_since_tournament_game": null,
      "away_days_since_tournament_game": null,
      "home_clinched_ncaa_bid": false,
      "away_clinched_ncaa_bid": false,
      "home_is_bubble_team": false,
      "away_is_bubble_team": false,
      "Point": -8.0
    },
    {
      "League": "NCAAB",
      "Event": "Kent St. @ Akron",
      "Injury Alert": "\u2014",
      "Selection": "Akron",
      "Market": "spreads",
      "Odds": -110,
      "Value (%)": 6.92,
      "Recommended Stake": 30.0,
      "Start Time": "Mar 13, 07:30 PM ET",
      "commence_time": "2026-03-13T23:30:00+00:00",
      "start_time": "2026-03-13T23:30:00+00:00",
      "model_prob": 0.5600690696269031,
      "implied_prob": 0.5,
      "point": -7.0,
      "home_team": "Akron",
      "away_team": "Kent St.",
      "is_home_b2b": false,
      "is_away_b2b": false,
      "underdog_value": false,
      "line_error": -12.07,
      "confidence_tier": "Medium",
      "reasoning_summary": "Our model sees 6.9% expected value on Akron -7.0 in this Spread\u2014the best NCAAB play we're highlighting today. Akron BARTHAG 0.00 (win probability). Kent St. BARTHAG 0.00 (win probability)",
      "is_conference_tournament": false,
      "home_seed": null,
      "away_seed": null,
      "home_days_since_tournament_game": null,
      "away_days_since_tournament_game": null,
      "home_clinched_ncaa_bid": false,
      "away_clinched_ncaa_bid": false,
      "home_is_bubble_team": false,
      "away_is_bubble_team": false,
      "Point": -7.0
    }
  ],
  "potd_picks": {
    "NCAAB Pick 1": null,
    "NCAAB Pick 2": {
      "League": "NCAAB Pick 2",
      "Event": "Kennesaw St @ Sam Houston",
      "Selection": "Sam Houston",
      "Market": "spreads",
      "Odds": -108,
      "Value (%)": 14.68,
      "point": -4.0,
      "Recommended Stake": 30.0,
      "Start Time": "Mar 13, 03:00 PM ET",
      "commence_time": "2026-03-13T19:00:00+00:00",
      "Injury Alert": "\u2014",
      "high_variance": false,
      "home_team": "Sam Houston",
      "away_team": "Kennesaw St",
      "model_prob": 0.5954283295257987,
      "confidence_tier": "High",
      "reasoning_summary": "Our model sees 14.7% expected value on Sam Houston -4.0 in this Spread\u2014the best NCAAB play we're highlighting today. Sam Houston BARTHAG 0.00 (win probability). Kennesaw St BARTHAG 0.00 (win probability)",
      "line_error": -4.67,
      "reason": "Our model sees 14.7% expected value on Sam Houston -4.0 in this Spread\u2014the best NCAAB play we're highlighting today. Sam Houston BARTHAG 0.00 (win probability). Kennesaw St BARTHAG 0.00 (win probability)",
      "Point": -4.0
    }
  },
  "timestamp": "2026-03-13T12:10:04.855790+00:00",
  "odds_source_meta": {
    "ncaab_espn_games": 0,
    "ncaab_espn_rows": 0,
    "ncaab_rundown_games": 27,
    "ncaab_rundown_rows": 132,
    "ncaab_merged_games": 27,
    "ncaab_odds_rows": 132,
    "used_ncaab_espn_primary": true
  },
  "value_plays_flagged_count": 38
}