{
  "card_date": "2026-05-27",
  "plays": [
    {
      "card_date": "2026-05-27",
      "event_id": "824432",
      "commence_time": "2026-05-27T17:10:00Z",
      "home_team": "Cleveland Guardians",
      "away_team": "Washington Nationals",
      "home_pitcher": "Gavin Williams",
      "away_pitcher": "Miles Mikolas",
      "market": "moneyline",
      "selection": "Washington Nationals",
      "odds_american": 163.0,
      "model_prob": 0.4395810233068478,
      "edge": 0.15609809129700958,
      "park_mult": 0.98
    },
    {
      "card_date": "2026-05-27",
      "event_id": "824104",
      "commence_time": "2026-05-27T23:40:00Z",
      "home_team": "Kansas City Royals",
      "away_team": "New York Yankees",
      "home_pitcher": "Noah Cameron",
      "away_pitcher": "Gerrit Cole",
      "market": "moneyline",
      "selection": "New York Yankees",
      "odds_american": -149.0,
      "model_prob": 0.6777976867360764,
      "edge": 0.13269546306901359,
      "park_mult": 1.04
    },
    {
      "card_date": "2026-05-27",
      "event_id": "822897",
      "commence_time": "2026-05-28T00:05:00Z",
      "home_team": "Texas Rangers",
      "away_team": "Houston Astros",
      "home_pitcher": "Jacob deGrom",
      "away_pitcher": "Mike Burrows",
      "market": "moneyline",
      "selection": "Houston Astros",
      "odds_american": 139.0,
      "model_prob": 0.46278313464550214,
      "edge": 0.10605169180274987,
      "park_mult": 1.02
    }
  ]
}